probe_params-0.1.2-py2.7-nspkg.pth
probe/params/codata.py
probe/params/__init__.py
probe/params/sim_params.py
probe/params/consts.py
probe_params-0.1.2.data/scripts/probe_params.py
probe_params-0.1.2.dist-info/top_level.txt
probe_params-0.1.2.dist-info/DESCRIPTION.rst
probe_params-0.1.2.dist-info/RECORD
probe_params-0.1.2.dist-info/metadata.json
probe_params-0.1.2.dist-info/METADATA
probe_params-0.1.2.dist-info/WHEEL
probe_params-0.1.2.dist-info/namespace_packages.txt
probe_params-0.1.2.dist-info/entry_points.txt
probe_params-0.1.2.dist-info/zip-safe
