Metadata-Version: 2.0
Name: probe-params
Version: 0.1.2
Summary: configure simulation parameters
Home-page: UNKNOWN
Author: Petr Zikan
Author-email: zikan.p@gmail.com
License: GPLv3
Platform: UNKNOWN
Requires-Dist: cleo
